{
 "cells": [
  {
   "cell_type": "markdown",
   "metadata": {},
   "source": [
    "# Байткод"
   ]
  },
  {
   "cell_type": "code",
   "execution_count": 1,
   "metadata": {},
   "outputs": [],
   "source": [
    "from newmodule import multiply"
   ]
  },
  {
   "cell_type": "code",
   "execution_count": 2,
   "metadata": {},
   "outputs": [
    {
     "data": {
      "text/plain": [
       "25"
      ]
     },
     "execution_count": 2,
     "metadata": {},
     "output_type": "execute_result"
    }
   ],
   "source": [
    "multiply(5,5)"
   ]
  },
  {
   "cell_type": "code",
   "execution_count": 3,
   "metadata": {},
   "outputs": [
    {
     "data": {
      "text/plain": [
       "['__annotations__',\n",
       " '__call__',\n",
       " '__class__',\n",
       " '__closure__',\n",
       " '__code__',\n",
       " '__defaults__',\n",
       " '__delattr__',\n",
       " '__dict__',\n",
       " '__dir__',\n",
       " '__doc__',\n",
       " '__eq__',\n",
       " '__format__',\n",
       " '__ge__',\n",
       " '__get__',\n",
       " '__getattribute__',\n",
       " '__globals__',\n",
       " '__gt__',\n",
       " '__hash__',\n",
       " '__init__',\n",
       " '__init_subclass__',\n",
       " '__kwdefaults__',\n",
       " '__le__',\n",
       " '__lt__',\n",
       " '__module__',\n",
       " '__name__',\n",
       " '__ne__',\n",
       " '__new__',\n",
       " '__qualname__',\n",
       " '__reduce__',\n",
       " '__reduce_ex__',\n",
       " '__repr__',\n",
       " '__setattr__',\n",
       " '__sizeof__',\n",
       " '__str__',\n",
       " '__subclasshook__']"
      ]
     },
     "execution_count": 3,
     "metadata": {},
     "output_type": "execute_result"
    }
   ],
   "source": [
    "dir(multiply)"
   ]
  },
  {
   "cell_type": "code",
   "execution_count": 4,
   "metadata": {},
   "outputs": [
    {
     "data": {
      "text/plain": [
       "<code object multiply at 0x111e0e4b0, file \"/Users/searge/Code/DiveinPython/w_1/playground/newmodule.py\", line 1>"
      ]
     },
     "execution_count": 4,
     "metadata": {},
     "output_type": "execute_result"
    }
   ],
   "source": [
    "multiply.__code__"
   ]
  },
  {
   "cell_type": "code",
   "execution_count": 5,
   "metadata": {},
   "outputs": [
    {
     "data": {
      "text/plain": [
       "b'|\\x00|\\x01\\x14\\x00S\\x00'"
      ]
     },
     "execution_count": 5,
     "metadata": {},
     "output_type": "execute_result"
    }
   ],
   "source": [
    "# Рядки байткоду\n",
    "multiply.__code__.co_code"
   ]
  },
  {
   "cell_type": "code",
   "execution_count": 6,
   "metadata": {},
   "outputs": [
    {
     "name": "stdout",
     "output_type": "stream",
     "text": [
      "  2           0 LOAD_FAST                0 (a)\n",
      "              2 LOAD_FAST                1 (b)\n",
      "              4 BINARY_MULTIPLY\n",
      "              6 RETURN_VALUE\n"
     ]
    }
   ],
   "source": [
    "import dis\n",
    "\n",
    "# Дизасамблюємо нашу функцію\n",
    "dis.dis(multiply)"
   ]
  },
  {
   "cell_type": "markdown",
   "metadata": {},
   "source": [
    "Каждая из этих инструкций делает какое-то действие. \n",
    "\n",
    "Давайте посмотрим на каждую инструкцию подробно. \n",
    "1. Первая — это `LOAD_FAST`, это инструкция, которая загружает содержимое переменной a в память и помещает его на стек. \n",
    "    - Стек — это структура данных, `last in — first out`, которая определена на уровне C и используется Python для того, чтобы манипулировать ходом выполнения программы. \n",
    "2. Как только переменная `a` помещена на стек, мы переходим ко второй инструкции, которая также `LOAD_FAST`, она делает то же самое со значением переменной `b`, помещает значение переменной `b` на стек.\n",
    "3. Следующая инструкция — это `BINARY_MULTIPLY`. \n",
    "    - `BINARY_MULTIPLY` говорит интерпретатору Python, что нужно взять два самых верхних значения на стеке и произвести их умножение. Заметьте, что мы могли передать в функцию значение любого типа. Могли передать целые числа, могли вещественные. Могли бы передать даже строки, например. Но в результате преобразования нашей функции в байт-код байт-код получился тем же самым. Типизация начинает по большому счету работать тогда, когда Python выполняет ту или иную инструкцию. В данном случае, когда выполняется инструкция `BINARY_MULTIPLY`, Python посмотрит на тип объектов, и, например, если это два числа, произведет умножение двух чисел. Результат умножения он поместит на вершину стека.\n",
    "4. И последняя инструкция — это `RETURN_VALUE`. \n",
    "    - `RETURN_VALUE` берет вершину стека, это результат умножения наших значений `a` и `b`, и возвращает его. \n",
    "    \n",
    "По большому счету, это то, как работает Python, как устроен байт-код, и любой код на Python, который вы будете писать, будет превращаться, компилироваться в байт-код."
   ]
  },
  {
   "cell_type": "markdown",
   "metadata": {},
   "source": [
    "Все эти инструкции задокументированы, их можно посмотреть как в исходном коде Python, так и в документации. Ну, и можно посмотреть на них сейчас, есть модуль в стандартной библиотеке `opcode`, который мы можем заимпортировать и напечатать."
   ]
  },
  {
   "cell_type": "code",
   "execution_count": 7,
   "metadata": {},
   "outputs": [
    {
     "name": "stdout",
     "output_type": "stream",
     "text": [
      "{'POP_TOP': 1, 'ROT_TWO': 2, 'ROT_THREE': 3, 'DUP_TOP': 4, 'DUP_TOP_TWO': 5, 'NOP': 9, 'UNARY_POSITIVE': 10, 'UNARY_NEGATIVE': 11, 'UNARY_NOT': 12, 'UNARY_INVERT': 15, 'BINARY_MATRIX_MULTIPLY': 16, 'INPLACE_MATRIX_MULTIPLY': 17, 'BINARY_POWER': 19, 'BINARY_MULTIPLY': 20, 'BINARY_MODULO': 22, 'BINARY_ADD': 23, 'BINARY_SUBTRACT': 24, 'BINARY_SUBSCR': 25, 'BINARY_FLOOR_DIVIDE': 26, 'BINARY_TRUE_DIVIDE': 27, 'INPLACE_FLOOR_DIVIDE': 28, 'INPLACE_TRUE_DIVIDE': 29, 'GET_AITER': 50, 'GET_ANEXT': 51, 'BEFORE_ASYNC_WITH': 52, 'INPLACE_ADD': 55, 'INPLACE_SUBTRACT': 56, 'INPLACE_MULTIPLY': 57, 'INPLACE_MODULO': 59, 'STORE_SUBSCR': 60, 'DELETE_SUBSCR': 61, 'BINARY_LSHIFT': 62, 'BINARY_RSHIFT': 63, 'BINARY_AND': 64, 'BINARY_XOR': 65, 'BINARY_OR': 66, 'INPLACE_POWER': 67, 'GET_ITER': 68, 'GET_YIELD_FROM_ITER': 69, 'PRINT_EXPR': 70, 'LOAD_BUILD_CLASS': 71, 'YIELD_FROM': 72, 'GET_AWAITABLE': 73, 'INPLACE_LSHIFT': 75, 'INPLACE_RSHIFT': 76, 'INPLACE_AND': 77, 'INPLACE_XOR': 78, 'INPLACE_OR': 79, 'BREAK_LOOP': 80, 'WITH_CLEANUP_START': 81, 'WITH_CLEANUP_FINISH': 82, 'RETURN_VALUE': 83, 'IMPORT_STAR': 84, 'SETUP_ANNOTATIONS': 85, 'YIELD_VALUE': 86, 'POP_BLOCK': 87, 'END_FINALLY': 88, 'POP_EXCEPT': 89, 'STORE_NAME': 90, 'DELETE_NAME': 91, 'UNPACK_SEQUENCE': 92, 'FOR_ITER': 93, 'UNPACK_EX': 94, 'STORE_ATTR': 95, 'DELETE_ATTR': 96, 'STORE_GLOBAL': 97, 'DELETE_GLOBAL': 98, 'LOAD_CONST': 100, 'LOAD_NAME': 101, 'BUILD_TUPLE': 102, 'BUILD_LIST': 103, 'BUILD_SET': 104, 'BUILD_MAP': 105, 'LOAD_ATTR': 106, 'COMPARE_OP': 107, 'IMPORT_NAME': 108, 'IMPORT_FROM': 109, 'JUMP_FORWARD': 110, 'JUMP_IF_FALSE_OR_POP': 111, 'JUMP_IF_TRUE_OR_POP': 112, 'JUMP_ABSOLUTE': 113, 'POP_JUMP_IF_FALSE': 114, 'POP_JUMP_IF_TRUE': 115, 'LOAD_GLOBAL': 116, 'CONTINUE_LOOP': 119, 'SETUP_LOOP': 120, 'SETUP_EXCEPT': 121, 'SETUP_FINALLY': 122, 'LOAD_FAST': 124, 'STORE_FAST': 125, 'DELETE_FAST': 126, 'RAISE_VARARGS': 130, 'CALL_FUNCTION': 131, 'MAKE_FUNCTION': 132, 'BUILD_SLICE': 133, 'LOAD_CLOSURE': 135, 'LOAD_DEREF': 136, 'STORE_DEREF': 137, 'DELETE_DEREF': 138, 'CALL_FUNCTION_KW': 141, 'CALL_FUNCTION_EX': 142, 'SETUP_WITH': 143, 'LIST_APPEND': 145, 'SET_ADD': 146, 'MAP_ADD': 147, 'LOAD_CLASSDEREF': 148, 'EXTENDED_ARG': 144, 'BUILD_LIST_UNPACK': 149, 'BUILD_MAP_UNPACK': 150, 'BUILD_MAP_UNPACK_WITH_CALL': 151, 'BUILD_TUPLE_UNPACK': 152, 'BUILD_SET_UNPACK': 153, 'SETUP_ASYNC_WITH': 154, 'FORMAT_VALUE': 155, 'BUILD_CONST_KEY_MAP': 156, 'BUILD_STRING': 157, 'BUILD_TUPLE_UNPACK_WITH_CALL': 158, 'LOAD_METHOD': 160, 'CALL_METHOD': 161}\n"
     ]
    }
   ],
   "source": [
    "import opcode\n",
    "\n",
    "print(opcode.opmap)"
   ]
  },
  {
   "cell_type": "code",
   "execution_count": null,
   "metadata": {},
   "outputs": [],
   "source": []
  }
 ],
 "metadata": {
  "kernel_info": {
   "name": "python3"
  },
  "kernelspec": {
   "display_name": "Python 3",
   "language": "python",
   "name": "python3"
  },
  "language_info": {
   "codemirror_mode": {
    "name": "ipython",
    "version": 3
   },
   "file_extension": ".py",
   "mimetype": "text/x-python",
   "name": "python",
   "nbconvert_exporter": "python",
   "pygments_lexer": "ipython3",
   "version": "3.7.1"
  },
  "nteract": {
   "version": "0.12.3"
  }
 },
 "nbformat": 4,
 "nbformat_minor": 4
}
